RealtimeSTT/__init__.py
RealtimeSTT/audio_input.py
RealtimeSTT/audio_recorder.py
RealtimeSTT/audio_recorder_client.py
RealtimeSTT/safepipe.py
RealtimeSTT/warmup_audio.wav
RealtimeSTT_server/__init__.py
RealtimeSTT_server/index.html
RealtimeSTT_server/install_packages.py
RealtimeSTT_server/stt_cli_client.py
RealtimeSTT_server/stt_server.py
realtimestt_multiclient-0.1.7.dist-info/METADATA
realtimestt_multiclient-0.1.7.dist-info/WHEEL
realtimestt_multiclient-0.1.7.dist-info/top_level.txt
realtimestt_multiclient-0.1.7.dist-info/RECORD
