Metadata-Version: 2.4
Name: realtimestt-multiclient
Version: 0.1.7
Summary: Realtime speech-to-text client and server with multi-client support
Author-email: Hendric Voß <hvoss@techfak.uni-bielefeld.de>, Vincent Emmerling <vemmerling@techfak.uni-bielefeld.de>
Project-URL: Homepage, https://scs.techfak.uni-bielefeld.de/
Project-URL: Repository, https://gitlab.ub.uni-bielefeld.de/scs/enrico/modules/realtimestt_multiclient
Keywords: speech,stt,whisper,realtime,audio,webrtcvad
Classifier: Programming Language :: Python :: 3
Classifier: Programming Language :: Python :: 3 :: Only
Classifier: Programming Language :: Python :: 3.10
Classifier: Programming Language :: Python :: 3.11
Classifier: Operating System :: OS Independent
Classifier: Intended Audience :: Developers
Classifier: Topic :: Multimedia :: Sound/Audio :: Speech
Requires-Python: >=3.10
Requires-Dist: PyAudio==0.2.14
Requires-Dist: faster-whisper==1.1.1
Requires-Dist: pvporcupine==1.9.5
Requires-Dist: webrtcvad-wheels==2.0.14
Requires-Dist: halo==0.0.31
Requires-Dist: torch
Requires-Dist: torchaudio
Requires-Dist: scipy==1.15.2
Requires-Dist: openwakeword>=0.4.0
Requires-Dist: websockets==15.0.1
Requires-Dist: websocket-client==1.8.0
Requires-Dist: soundfile==0.13.1
Requires-Dist: pytest
